music_dl/__init__.py
music_dl/__main__.py
music_dl/__version__.py
music_dl/api.py
music_dl/config.py
music_dl/exceptions.py
music_dl/song.py
music_dl/source.py
music_dl/utils.py
music_dl/addons/__init__.py
music_dl/addons/baidu.py
music_dl/addons/kugou.py
music_dl/addons/migu.py
music_dl/addons/netease.py
music_dl/addons/qq.py
music_dl/addons/xiami.py
tests/__init__.py
tests/test_addon_baidu.py
tests/test_addon_kugou.py
tests/test_addon_netease.py
tests/test_addon_qq.py
tests/test_addon_xiami.py
tests/test_config.py
tests/test_main.py
tests/test_song.py
tests/test_source.py
tests/test_utils.py
pymusic_dl-3.0.1.dist-info/LICENSE
pymusic_dl-3.0.1.dist-info/METADATA
pymusic_dl-3.0.1.dist-info/WHEEL
pymusic_dl-3.0.1.dist-info/entry_points.txt
pymusic_dl-3.0.1.dist-info/top_level.txt
pymusic_dl-3.0.1.dist-info/RECORD
